.gitignore
LICENSE
MANIFEST.in
README
setup.cfg
setup.py
brutha/__init__.py
brutha/__main__.py
brutha/directory.py
brutha/file.py
brutha/output.py
brutha/tree.py
brutha/util.py
brutha.egg-info/PKG-INFO
brutha.egg-info/SOURCES.txt
brutha.egg-info/dependency_links.txt
brutha.egg-info/entry_points.txt
brutha.egg-info/requires.txt
brutha.egg-info/top_level.txt