Metadata-Version: 1.1
Name: brutha
Version: 1.1.0
Summary: Sync FLAC music files to Ogg Vorbis (or keep lossy as-is)
Home-page: http://git.p.engu.in/laurentb/brutha/
Author: Laurent Bachelier
Author-email: laurent@bachelier.name
License: UNKNOWN
Platform: UNKNOWN
Classifier: Programming Language :: Python :: 2
Classifier: Programming Language :: Python :: 2.6
Classifier: Programming Language :: Python :: 2.7
Classifier: Operating System :: POSIX
Classifier: Environment :: Console
Classifier: License :: OSI Approved :: GNU General Public License v2 or later (GPLv2+)
Classifier: Topic :: Multimedia :: Sound/Audio :: Conversion
